NaviNIBS_Simulated_Tools/.git/COMMIT_EDITMSG
NaviNIBS_Simulated_Tools/.git/config
NaviNIBS_Simulated_Tools/.git/description
NaviNIBS_Simulated_Tools/.git/FETCH_HEAD
NaviNIBS_Simulated_Tools/.git/HEAD
NaviNIBS_Simulated_Tools/.git/hooks/applypatch-msg.sample
NaviNIBS_Simulated_Tools/.git/hooks/commit-msg.sample
NaviNIBS_Simulated_Tools/.git/hooks/fsmonitor-watchman.sample
NaviNIBS_Simulated_Tools/.git/hooks/post-update.sample
NaviNIBS_Simulated_Tools/.git/hooks/pre-applypatch.sample
NaviNIBS_Simulated_Tools/.git/hooks/pre-commit.sample
NaviNIBS_Simulated_Tools/.git/hooks/pre-push.sample
NaviNIBS_Simulated_Tools/.git/hooks/pre-rebase.sample
NaviNIBS_Simulated_Tools/.git/hooks/pre-receive.sample
NaviNIBS_Simulated_Tools/.git/hooks/prepare-commit-msg.sample
NaviNIBS_Simulated_Tools/.git/hooks/update.sample
NaviNIBS_Simulated_Tools/.git/index
NaviNIBS_Simulated_Tools/.git/info/exclude
NaviNIBS_Simulated_Tools/.git/logs/HEAD
NaviNIBS_Simulated_Tools/.git/logs/refs/heads/main
NaviNIBS_Simulated_Tools/.git/logs/refs/remotes/origin/HEAD
NaviNIBS_Simulated_Tools/.git/logs/refs/remotes/origin/main
NaviNIBS_Simulated_Tools/.git/objects/00/926538e1d8d2dc1d68e993badcffe58980ed4b
NaviNIBS_Simulated_Tools/.git/objects/01/dfefcb11f2c57ac1fbdc33a59764622bfccab4
NaviNIBS_Simulated_Tools/.git/objects/02/4d809cde6e8a633ea1757a54246d82cb5a1383
NaviNIBS_Simulated_Tools/.git/objects/04/c6023aa610aeb948cec1583e4a2eb0be7b6804
NaviNIBS_Simulated_Tools/.git/objects/06/3f35d942fa0b2d0dd60fbd9f8c7141cd58b152
NaviNIBS_Simulated_Tools/.git/objects/08/2c220fb1bcd46cd19aa35bd6e96bbfa480dc33
NaviNIBS_Simulated_Tools/.git/objects/0a/041280bd00a9d068f503b8ee7ce35214bd24a1
NaviNIBS_Simulated_Tools/.git/objects/0c/1daa8e3e751cc71d186f06b6e89a6d1f7100f3
NaviNIBS_Simulated_Tools/.git/objects/0d/012471afc108a6da2190c9573c9b1b352adacb
NaviNIBS_Simulated_Tools/.git/objects/0d/0abeda0de75a96e146243ace574aca1ee0cfd0
NaviNIBS_Simulated_Tools/.git/objects/0d/dc65ef5f21c07363f7e9b74a07b5fabbada0d7
navinibs_simulated_tools-0.1.6.dist-info/COPYING
navinibs_simulated_tools-0.1.6.dist-info/COPYING.LESSER
navinibs_simulated_tools-0.1.6.dist-info/METADATA
navinibs_simulated_tools-0.1.6.dist-info/WHEEL
navinibs_simulated_tools-0.1.6.dist-info/RECORD
