Metadata-Version: 2.3
Name: NaviNIBS_Simulated_Tools
Version: 0.1.6
Summary: NaviNIBS addon for simulating tool poses
License: LGPL-3.0-only
Author: Christopher C. Cline
Author-email: chriscline@users.noreply.github.com
Requires-Python: >=3.10,<3.14
Classifier: License :: OSI Approved :: GNU Lesser General Public License v3 (LGPLv3)
Classifier: Programming Language :: Python :: 3
Classifier: Programming Language :: Python :: 3.10
Classifier: Programming Language :: Python :: 3.11
Classifier: Programming Language :: Python :: 3.12
Classifier: Programming Language :: Python :: 3.13
Requires-Dist: navinibs (>=0.1.5)
Project-URL: Documentation, https://precisionneurolab.github.io/navinibs-docs
Project-URL: Homepage, https://github.com/PrecisionNeuroLab/NaviNIBS
Project-URL: Repository, https://github.com/PrecisionNeuroLab/NaviNIBS_Simulated_Tools
